dict_wrapper/__init__.py
dict_wrapper/dict_to_obj.py
dict_wrapper-0.0.4.dist-info/LICENSE
dict_wrapper-0.0.4.dist-info/METADATA
dict_wrapper-0.0.4.dist-info/WHEEL
dict_wrapper-0.0.4.dist-info/top_level.txt
dict_wrapper-0.0.4.dist-info/RECORD
