Metadata-Version: 2.1
Name: dict-wrapper
Version: 0.0.4
Summary: A userful package to use '.' to visit value of dict
Home-page: https://github.com/Yyonging/dict_wrapper
Author: duanyongqiang
Author-email: sysuduanyongqiang@163.com
License: UNKNOWN
Platform: UNKNOWN
Classifier: Programming Language :: Python :: 3
Classifier: License :: OSI Approved :: GNU General Public License v2 (GPLv2)
Classifier: Operating System :: OS Independent
Requires-Python: >=3.4
